README.md
setup.py
Flask_Query.egg-info/PKG-INFO
Flask_Query.egg-info/SOURCES.txt
Flask_Query.egg-info/dependency_links.txt
Flask_Query.egg-info/not-zip-safe
Flask_Query.egg-info/requires.txt
Flask_Query.egg-info/top_level.txt
flask_query/AndCondition.py
flask_query/BaseQuery.py
flask_query/BetweenCondition.py
flask_query/BetweenConditionBuilder.py
flask_query/CommonExpressBuilder.py
flask_query/ConditionInterface.py
flask_query/ConjunctionCondition.py
flask_query/ConjunctionConditionBuilder.py
flask_query/DB.py
flask_query/ExpressionInterface.py
flask_query/Handler.py
flask_query/HashCondition.py
flask_query/HashConditionBuilder.py
flask_query/InCondition.py
flask_query/InConditionBuilder.py
flask_query/LikeCondition.py
flask_query/LikeConditionBuilder.py
flask_query/MysqlDB.py
flask_query/NotCondition.py
flask_query/NotConditionBuilder.py
flask_query/OrCondition.py
flask_query/PoolDB.py
flask_query/Query.py
flask_query/QueryBuilder.py
flask_query/SimpleCondition.py
flask_query/SimpleConditionBuilder.py
flask_query/__init__.py